sttpy/__init__.py
sttpy/__main__.py
sttpy/config.py
sttpy/stt.py
sttpy/commands/__init__.py
sttpy/commands/backspace.py
sttpy/commands/chatgpt.py
sttpy/commands/comma.py
sttpy/commands/delete.py
sttpy/commands/git.py
sttpy/commands/hey_jarvis.py
sttpy/commands/paste.py
sttpy/commands/space.py
sttpy/commands/undo.py
sttpy/utils/__init__.py
sttpy/utils/hotkey.py
sttpy-0.1.5.dist-info/METADATA
sttpy-0.1.5.dist-info/WHEEL
sttpy-0.1.5.dist-info/entry_points.txt
sttpy-0.1.5.dist-info/RECORD
