Metadata-Version: 2.4
Name: sttpy
Version: 0.1.5
Summary: Dead simple speech-to-text
Requires-Python: <3.13,>=3.9
Requires-Dist: click>=8.1.7
Requires-Dist: keyboard>=0.13.5
Requires-Dist: langchain-community>=0.3.12
Requires-Dist: langchain>=0.3.12
Requires-Dist: openai-whisper>=20240930
Requires-Dist: pygetwindow>=0.0.9
Requires-Dist: pyperclip>=1.9.0
Requires-Dist: pytest>=8.3.4
Requires-Dist: sounddevice>=0.5.1
Provides-Extra: cuda
Requires-Dist: numba>=0.54.0; extra == 'cuda'
Requires-Dist: torch>=2.5.1; extra == 'cuda'
Provides-Extra: rocm
Requires-Dist: numba>=0.54.0; extra == 'rocm'
Requires-Dist: torch>=2.5.1; extra == 'rocm'
